Workbook

Sheet Dados
A1: title | B1: totalScore | C1: reviewsCount | D1: street | E1: city | F1: state | G1: countryCode | H1: website | I1: phone | J1: categoryName | K1: url | L1: has_website | M1: has_website_boxplot | N1: reviewsCount_boxplot
A2: – R. Riachuelo | B2: 0 | C2: 0 | D2: R. Riachuelo, 124 | E2: Rio de Janeiro | F2: Rio de Janeiro | G2: BR | J2: Hotel | K2: https://www.google.com/maps/search/?api=1&query=%E2%80%93%20R.%20Riachuelo&query_place_id=ChIJx3tYmNh_mQARim_DQCoZnBs | L2: SEM | M2: SEM | N2: 0
A3: 37 hostel | B3: 0 | C3: 0 | D3: R. do Morro, 37 | E3: Ipubi | F3: Pernambuco | G3: BR | H3: https://www.facebook.com/37hostel/ | I3: +55 84 99221-5964 | J3: Motel | K3: https://www.google.com/maps/search/?api=1&query=37%20hostel&query_place_id=ChIJExHL9OaPsgcR2uJEQuUkNHg | L3: COM | M3: SIM | N3: 0
A4: 44 Residence | B4: 0 | C4: 0 | D4: R. Ó de Almeida, 545 | E4: Belém | F4: Pará | G4: BR | H4: https://44residence.com/ | J4: Hotel | K4: https://www.google.com/maps/search/?api=1&query=44%20Residence&query_place_id=ChIJce4K7ROPpJIR0if_T7CGzp4 | L4: COM | M4: COM | N4: 0
A5: A Silva da Costa | B5: 0 | C5: 0 | D5: R. Europa | E5: São Luís | F5: Maranhão | G5: BR | J5: Hotel | K5: https://www.google.com/maps/search/?api=1&query=A%20Silva%20da%20Costa&query_place_id=ChIJ8ebmFwCT9gcRbHBqzN0ewJ4 | L5: SEM | M5: SEM | N5: 0
A6: Aa | B6: 0 | C6: 0 | D6: Rua Dallas, A15 | E6: Manaus | F6: Amazonas | G6: BR | J6: Albergue | K6: https://www.google.com/maps/search/?api=1&query=Aa&query_place_id=ChIJQcBWYcobbJIR40CsDmThE2s | L6: SEM | M6: SEM | N6: 0
A7: Abrigo Caramelos do Vale | B7: 0 | C7: 0 | D7: Av. Edgar Píres de Castro, 3899 | E7: Porto Alegre | F7: Rio Grande do Sul | G7: BR | J7: Albergue | K7: https://www.google.com/maps/search/?api=1&query=Abrigo%20Caramelos%20do%20Vale&query_place_id=ChIJ1foMZQCbGZUR2U3DRUuXKuQ | L7: SEM | M7: SEM | N7: 0
A8: Acai Motel | B8: 0 | C8: 0 | D8: GO-320, km 04 | E8: Paraúna | F8: Goiás | G8: BR | I8: +55 64 99319-1429 | J8: Motel | K8: https://www.google.com/maps/search/?api=1&query=Acai%20Motel&query_place_id=ChIJPxAmRT_vYJMRwGU35sPIqls | L8: SEM | M8: SEM | N8: 0
A9: Açai Palace Hotel | B9: 0 | C9: 0 | D9: Av. Antônio Coelho de Carvalho, 1399 | E9: Macapá | F9: Amapá | G9: BR | I9: +55 96 3223-4899 | J9: Hotel | K9: https://www.google.com/maps/search/?api=1&query=A%C3%A7ai%20Palace%20Hotel&query_place_id=ChIJD9z8qw7hYY0ReGZVhb7xNnU | L9: SEM | M9: SEM | N9: 0
A10: Adriane | B10: 0 | C10: 0 | D10: R. Gomes Jardim, 201 | E10: Porto Alegre | F10: Rio Grande do Sul | G10: BR | J10: Hotel | K10: https://www.google.com/maps/search/?api=1&query=Adriane&query_place_id=ChIJAeCJYTN5GZURBQNJ-f48l6Q | L10: SEM | M10: SEM | N10: 0
A11: Airbnb do Luís | B11: 0 | C11: 0 | D11: R. Dois | E11: São Luís | F11: Maranhão | G11: BR | I11: +55 98 98831-2774 | J11: Apart hotel | K11: https://www.google.com/maps/search/?api=1&query=Airbnb%20do%20Lu%C3%ADs&query_place_id=ChIJRX4fCaeR9gcRGaYodcLyUW4 | L11: SEM | M11: SEM | N11: 0
A12: alameda das flavias | B12: 0 | C12: 0 | D12: Av. dos Xavantes, 770 | E12: Macapá | F12: Amapá | G12: BR | J12: Hotel | K12: https://www.google.com/maps/search/?api=1&query=alameda%20das%20flavias&query_place_id=ChIJ00WCSQDhYY0R9vBSbogjcaQ | L12: SEM | M12: SEM | N12: 0
A13: Albergue | B13: 0 | C13: 0 | D13: Av. Sete de Setembro | E13: Petrolina | F13: Pernambuco | G13: BR | J13: Albergue | K13: https://www.google.com/maps/search/?api=1&query=Albergue&query_place_id=ChIJDZ2cfQBxcwcRCG9nJACWOUI | L13: SEM | M13: SEM | N13: 0
A14: Albergue | B14: 0 | C14: 0 | D14: R. das Caravelas, 612 | E14: São Luís | F14: Maranhão | G14: BR | J14: Apartamento | K14: https://www.google.com/maps/search/?api=1&query=Albergue&query_place_id=ChIJ3QgtEayb9gcRIXuIKJefPlU | L14: SEM | M14: SEM | N14: 0
A15: albergue bisca | B15: 0 | C15: 0 | D15: R. Adolfo Muhlman, 84 | E15: Pinhais | F15: Paraná | G15: BR | J15: Albergue | K15: https://www.google.com/maps/search/?api=1&query=albergue%20bisca&query_place_id=ChIJXWdmBADv3JQRednpwPsm2sA | L15: SEM | M15: SEM | N15: 0
A16: Albergue Gravatá | B16: 0 | C16: 0 | D16: Av. Governador Agamenon Magalhães, 317 | E16: Gravatá | F16: Pernambuco | G16: BR | J16: Albergue | K16: https://www.google.com/maps/search/?api=1&query=Albergue%20Gravat%C3%A1&query_place_id=ChIJOR7tRihIqgcR6pcBdYpG8gw | L16: SEM | M16: SEM | N16: 0
A17: Aldeia Multiétinica do Tio Marquinho | B17: 0 | C17: 0 | D17: Tv. Humaitá, 3298 | E17: Belém | F17: Pará | G17: BR | I17: +55 91 98523-8072 | J17: Hospedagem | K17: https://www.google.com/maps/search/?api=1&query=Aldeia%20Multi%C3%A9tinica%20do%20Tio%20Marquinho&query_place_id=ChIJMbvEWzyNpJIRqquOTubrgPU | L17: SEM | M17: SEM | N17: 0
A18: Alimentos | B18: 0 | C18: 0 | D18: R. Santos Dumont, 15 | E18: Crato | F18: Ceará | G18: BR | I18: +55 88 99627-2049 | J18: Albergue | K18: https://www.google.com/maps/search/?api=1&query=Alimentos&query_place_id=ChIJLbp6l2SEoQcR5OK3S9-3PJ4 | L18: SEM | M18: SEM | N18: 0
A19: Alojamento São Francisco | B19: 0 | C19: 0 | D19: Av. João Basílio Tavares, 335 | E19: Mazagão | F19: Amapá | G19: BR | J19: Hotel | K19: https://www.google.com/maps/search/?api=1&query=Alojamento%20S%C3%A3o%20Francisco&query_place_id=ChIJ35Edz9wHnpIRCkmhJJmTxfU | L19: SEM | M19: SEM | N19: 0
A20: Alu Flat lounge | B20: 0 | C20: 0 | D20: R. Fernando Cutrim, s/n | E20: São Luís | F20: Maranhão | G20: BR | I20: +55 98 98519-4215 | J20: Hotel | K20: https://www.google.com/maps/search/?api=1&query=Alu%20Flat%20lounge&query_place_id=ChIJMavuXvuN9gcRMPCr892piF4 | L20: SEM | M20: SEM | N20: 0
A21: ALU HOTEL | B21: 0 | C21: 0 | D21: R. das Paparaubas, 03 - QD 11 | E21: São Luís | F21: Maranhão | G21: BR | I21: +55 98 98519-4215 | J21: Hotel | K21: https://www.google.com/maps/search/?api=1&query=ALU%20HOTEL&query_place_id=ChIJlSlSmfOP9gcR0uNcgrlIG1k | L21: SEM | M21: SEM | N21: 0
A22: Aluguel de quarto - Fernando Leão | B22: 0 | C22: 0 | D22: Ao lado do Supermercado vitória, na - R. Londrina, 22 - sobrado | E22: Barro Alto | F22: Goiás | G22: BR | I22: +55 62 99800-9864 | J22: Hotel | K22: https://www.google.com/maps/search/?api=1&query=Aluguel%20de%20quarto%20-%20Fernando%20Le%C3%A3o&query_place_id=ChIJ59_p5dZNQ5MR7XmMhuVI3_o | L22: SEM | M22: SEM | N22: 0
A23: Aluguel de quartos em POA Unidade João Pessoa | B23: 0 | C23: 0 | D23: Av. João Pessoa, 817 | E23: Porto Alegre | F23: Rio Grande do Sul | G23: BR | I23: +55 51 98162-5160 | J23: Hotel | K23: https://www.google.com/maps/search/?api=1&query=Aluguel%20de%20quartos%20em%20POA%20Unidade%20Jo%C3%A3o%20Pessoa&query_place_id=ChIJgfskTkJ5GZURrRcpjy_ETz4 | L23: SEM | M23: SEM | N23: 0
A24: Aluguel Temporada Guarapari | B24: 0 | C24: 0 | D24: Av. Praiana, 1451 | E24: Guarapari | F24: Espírito Santo | G24: BR | I24: +55 67 98458-2048 | J24: Apart hotel | K24: https://www.google.com/maps/search/?api=1&query=Aluguel%20Temporada%20Guarapari&query_place_id=ChIJzXv0r8xXuAARxSLgwQyYoOU | L24: SEM | M24: SEM | N24: 0
A25: Alyssacraft1blox | B25: 0 | C25: 0 | D25: R. Manduca Nunes, 12 | E25: Porto Alegre | F25: Rio Grande do Sul | G25: BR | I25: +55 51 99206-5721 | J25: Albergue | K25: https://www.google.com/maps/search/?api=1&query=Alyssacraft1blox&query_place_id=ChIJ6bDxobuDGZUR4xuJYPh64PQ | L25: SEM | M25: SEM | N25: 0
A26: AMAZON BACK PACKERS DJALMA | B26: 0 | C26: 0 | D26: MINISHOPPING BEVELY HILLS - Av. Djalma Batista, 2339 - PISO 2 | E26: Manaus | F26: Amazonas | G26: BR | I26: +55 92 99489-7252 | J26: Albergue | K26: https://www.google.com/maps/search/?api=1&query=AMAZON%20BACK%20PACKERS%20DJALMA&query_place_id=ChIJ9fYP3acabJIRMdmozQ97WuY | L26: SEM | M26: SEM | N26: 0
A27: Amazon Geo | B27: 0 | C27: 0 | D27: Edifício Palácio do Comercio - Av. Eduardo Ribeiro, 1303 | E27: Manaus | F27: Amazonas | G27: BR | H27: http://amazongeo.com/ | J27: Hotel | K27: https://www.google.com/maps/search/?api=1&query=Amazon%20Geo&query_place_id=ChIJlTmAC30FbJIRZpdp37cSihY | L27: COM | M27: COM | N27: 0
A28: Amazonas | B28: 0 | C28: 0 | E28: Ouricuri | F28: Pernambuco | G28: BR | J28: Hotel | K28: https://www.google.com/maps/search/?api=1&query=Amazonas&query_place_id=ChIJW44NTaSNnwcRSoaCCaN5MDk | L28: SEM | M28: SEM | N28: 0
A29: American Flat Apartamento Aluguel SLZ | B29: 0 | C29: 0 | D29: American Flat - Av. dos Holandeses, S/N | E29: São Luís | F29: Maranhão | G29: BR | H29: https://www.booking.com/hotel/br/lindo-flat-apartamento-proximo-a-praia-com-vista.pt-br.html | J29: Hotel | K29: https://www.google.com/maps/search/?api=1&query=American%20Flat%20Apartamento%20Aluguel%20SLZ&query_place_id=ChIJBwP-2SKN9gcROSQhP34XTi0 | L29: COM | M29: COM | N29: 0
A30: AMILL HOSTEL | B30: 0 | C30: 0 | D30: R. Tapajós, 512 | E30: Manaus | F30: Amazonas | G30: BR | H30: https://amill-hostel.negocio.site/?utm_source=gmb&utm_medium=referral | J30: Hotel | K30: https://www.google.com/maps/search/?api=1&query=AMILL%20HOSTEL&query_place_id=ChIJ-cQB7AEFbJIRSjNKraPWdjw | L30: COM | M30: COM | N30: 0
A31: Anauê Jungle Chalés | B31: 0 | C31: 0 | D31: R. Cedrinho | E31: Manaus | F31: Amazonas | G31: BR | H31: https://anauejunglechales.com.br/ | I31: +55 92 99419-7052 | J31: Pousada | K31: https://www.google.com/maps/search/?api=1&query=Anau%C3%AA%20Jungle%20Chal%C3%A9s&query_place_id=ChIJ9RFbrLo9bJIRD_oDb1RL84U | L31: COM | M31: COM | N31: 0
A32: Anburgue noite | B32: 0 | C32: 0 | D32: R. Furtunato Silva, 224 | E32: Pedra Branca | F32: Ceará | G32: BR | J32: Albergue | K32: https://www.google.com/maps/search/?api=1&query=Anburgue%20noite&query_place_id=ChIJNegQoHafvQcRzytNO3qWNY8 | L32: SEM | M32: SEM | N32: 0
A33: anjos da fe | B33: 0 | C33: 0 | D33: R. dos Cedros, casa 12 | E33: São Luís | F33: Maranhão | G33: BR | H33: https://anjosdafe.lojavirtualnuvem.com.br/ | I33: +55 98 99220-0800 | J33: Alojamento | K33: https://www.google.com/maps/search/?api=1&query=anjos%20da%20fe&query_place_id=ChIJFWtsUxiP9gcRskX_hR0T-DQ | L33: COM | M33: COM | N33: 0
A34: Annas Hostel | B34: 0 | C34: 0 | D34: Rua Buritis, Quadra 23, Lote 11, S/n | E34: Alto Paraíso de Goiás | F34: Goiás | G34: BR | I34: +55 61 99339-0319 | J34: Albergue | K34: https://www.google.com/maps/search/?api=1&query=Annas%20Hostel&query_place_id=ChIJB3T1rHsLRZMR-UFDlA6xBOY | L34: SEM | M34: SEM | N34: 0
A35: Apart em Belém Modern | B35: 0 | C35: 0 | D35: R. Antônio Barreto, 140 - apt. 1402 | E35: Belém | F35: Pará | G35: BR | H35: https://maistelecombelem.wixsite.com/aptoembelemodern | I35: +55 91 98115-6647 | J35: Apartamento | K35: https://www.google.com/maps/search/?api=1&query=Apart%20em%20Bel%C3%A9m%20Modern&query_place_id=ChIJCdMua_WPpJIRlqDE5FPLoBo | L35: COM | M35: COM | N35: 0
A36: APART HOTEL MANAUS UN 2525 | B36: 0 | C36: 0 | D36: Av. Constantino Nery, 2525 | E36: Manaus | F36: Amazonas | G36: BR | I36: +55 92 98446-8871 | J36: Albergue | K36: https://www.google.com/maps/search/?api=1&query=APART%20HOTEL%20MANAUS%20UN%202525&query_place_id=ChIJ5d4b7QcQbJIRGWnbji1vJAk | L36: SEM | M36: SEM | N36: 0
A37: Apart Hotel Mont Blanc | B37: 0 | C37: 0 | D37: Av. Fab, 3744 | E37: Macapá | F37: Amapá | G37: BR | J37: Hotel | K37: https://www.google.com/maps/search/?api=1&query=Apart%20Hotel%20Mont%20Blanc&query_place_id=ChIJUxw1H5DhYY0RH2p4MxONNCY | L37: SEM | M37: SEM | N37: 0
A38: Apart Hotel Pioneiro | B38: 0 | C38: 0 | D38: Av. Mercúrio Norte | E38: Chapadão do Céu | F38: Goiás | G38: BR | I38: +55 64 99911-2009 | J38: Hotel | K38: https://www.google.com/maps/search/?api=1&query=Apart%20Hotel%20Pioneiro&query_place_id=ChIJq10YcPBVnZQRwzh9IOEnW_E | L38: SEM | M38: SEM | N38: 0
A39: Apartamento | B39: 0 | C39: 0 | D39: R. Costa Júnior, 1233 | E39: Jacarezinho | F39: Paraná | G39: BR | H39: https://www.facebook.com/ricar.condominios.5 | I39: +55 43 99880-6723 | J39: Hotel | K39: https://www.google.com/maps/search/?api=1&query=Apartamentos&query_place_id=ChIJ16baFVYmwJQRvQOv5Nf69BU | L39: COM | M39: COM | N39: 0
A40: Apartamento 303 | B40: 0 | C40: 0 | D40: Av. Liberdade, 3 - apartamento 303 | E40: Olinda | F40: Pernambuco | G40: BR | I40: +55 81 97900-4985 | J40: Albergue | K40: https://www.google.com/maps/search/?api=1&query=Apartamento%20303&query_place_id=ChIJ4QMhqbsiqwcRLSEf8rLV9Ms | L40: SEM | M40: SEM | N40: 0
A41: Apartamento do Topázio | B41: 0 | C41: 0 | D41: Passagem São José, 5 | E41: Belém | F41: Pará | G41: BR | J41: Hotel | K41: https://www.google.com/maps/search/?api=1&query=Apartamento%20do%20Top%C3%A1zio&query_place_id=ChIJFZfGGQCNpJIRgUAHuVnBmv4 | L41: SEM | M41: SEM | N41: 0
A42: APARTAMENTO SEMI MOBILIADO 301 | B42: 0 | C42: 0 | D42: Av. Pastor Ernesto Schlieper, 85 | E42: Porto Alegre | F42: Rio Grande do Sul | G42: BR | I42: +55 51 99113-4949 | J42: Apartamento | K42: https://www.google.com/maps/search/?api=1&query=APARTAMENTO%20SEMI%20MOBILIADO%20301&query_place_id=ChIJaym6srZ3GZURq5LaP9LucZY | L42: SEM | M42: SEM | N42: 0
A43: Apartamento Temporada Pls | B43: 0 | C43: 0 | D43: R. Danilo Mendonça, Qd. 19 - Lt 41 (esquina | E43: Palmeiras de Goiás | F43: Goiás | G43: BR | I43: +55 64 99950-6805 | J43: Hospedagem | K43: https://www.google.com/maps/search/?api=1&query=Apartamento%20Temporada%20Pls&query_place_id=ChIJs88lmncjXpMRmIfSEt8j6NU | L43: SEM | M43: SEM | N43: 0
A44: Apartamento tipo suites belem pra temporada | B44: 0 | C44: 0 | D44: R. Domingos Marreiros, 1769 | E44: Belém | F44: Pará | G44: BR | I44: +55 96 99100-5086 | J44: Apartamento | K44: https://www.google.com/maps/search/?api=1&query=Apartamento%20tipo%20suites%20belem%20pra%20temporada&query_place_id=ChIJA8wQUW6NpJIRAHiNHGb1-vQ | L44: SEM | M44: SEM | N44: 0
A45: ARIES HOSPEDARIA | B45: 0 | C45: 0 | D45: R. Buenos Aires, 82 | E45: Rio de Janeiro | F45: Rio de Janeiro | G45: BR | J45: Hotel | K45: https://www.google.com/maps/search/?api=1&query=ARIES%20HOSPEDARIA&query_place_id=ChIJI_t0g15_mQARxXkddJKBh5M | L45: SEM | M45: SEM | N45: 0
A46: asa da sogra | B46: 0 | C46: 0 | D46: R. Augusto dos Anjos, 1 | E46: São Luís | F46: Maranhão | G46: BR | J46: Cama e café | K46: https://www.google.com/maps/search/?api=1&query=asa%20da%20sogra&query_place_id=ChIJxd_AfACP9gcRIa2_dP8ypIc | L46: SEM | M46: SEM | N46: 0
A47: Associação ABPEC | B47: 0 | C47: 0 | D47: Vila Coquilho, 7 | E47: São Luís | F47: Maranhão | G47: BR | J47: Hotel | K47: https://www.google.com/maps/search/?api=1&query=Associa%C3%A7%C3%A3o%20ABPEC&query_place_id=ChIJqWIjQzCd9gcRUhdCg_A0ZsA | L47: SEM | M47: SEM | N47: 0
A48: Associação Brasileira da Ind de Hotéis do Pará | B48: 0 | C48: 0 | D48: Av. Pres. Vargas, 882 | E48: Belém | F48: Pará | G48: BR | J48: Hotel | K48: https://www.google.com/maps/search/?api=1&query=Associa%C3%A7%C3%A3o%20Brasileira%20da%20Ind%20de%20Hot%C3%A9is%20do%20Par%C3%A1&query_place_id=ChIJcZ5N342OpJIRWgdVGqDXV78 | L48: SEM | M48: SEM | N48: 0
A49: Avenida das Safiras | B49: 0 | C49: 0 | D49: Marginal - BR-163, KM-1185 | E49: Itaituba | F49: Pará | G49: BR | J49: Hotel | K49: https://www.google.com/maps/search/?api=1&query=Avenida%20das%20Safiras&query_place_id=ChIJW7BVCAANWJIRmJ5DdPDVo1I | L49: SEM | M49: SEM | N49: 0
A50: Baeh Buenos Aires Equip Hoteleir | B50: 0 | C50: 0 | D50: R. Regente Feijó, 51 | E50: Rio de Janeiro | F50: Rio de Janeiro | G50: BR | J50: Hotel | K50: https://www.google.com/maps/search/?api=1&query=Baeh%20Buenos%20Aires%20Equip%20Hoteleir&query_place_id=ChIJ5wCrgGh_mQARzIFUqzSzKoA | L50: SEM | M50: SEM | N50: 0
A51: Bahs | B51: 0 | C51: 0 | E51: Altamira | F51: Pará | G51: BR | J51: Cama e café | K51: https://www.google.com/maps/search/?api=1&query=Bahs&query_place_id=ChIJ8exXdwAt_5IRrBD4wJaVn_0 | L51: SEM | M51: SEM | N51: 0
A52: Banzeiro Hostel | B52: 0 | C52: 0 | D52: Passagem José Bonifácio, 183 | E52: Macapá | F52: Amapá | G52: BR | J52: Hotel | K52: https://www.google.com/maps/search/?api=1&query=Banzeiro%20Hostel&query_place_id=ChIJ39QyVyzhYY0RZAK8nTILUhw | L52: SEM | M52: SEM | N52: 0
A53: BARRACO DO LUIS | B53: 0 | C53: 0 | E53: Rurópolis | F53: Pará | G53: BR | J53: Albergue | K53: https://www.google.com/maps/search/?api=1&query=BARRACO%20DO%20LUIS&query_place_id=ChIJizW5TNxd9ZIROSevETyWvGU | L53: SEM | M53: SEM | N53: 0
A54: Batistão House | B54: 0 | C54: 0 | D54: Travessa Siqueira Mendes | E54: Belém | F54: Pará | G54: BR | I54: +55 91 99390-1005 | J54: Hotel | K54: https://www.google.com/maps/search/?api=1&query=Batist%C3%A3o%20House&query_place_id=ChIJ1_742xtrpJIRPF5JkHlvKbg | L54: SEM | M54: SEM | N54: 0
A55: BBB Rooms Centro Belem PA | B55: 0 | C55: 0 | D55: R. Aristides Lobo, 485 | E55: Belém | F55: Pará | G55: BR | J55: Hotel | K55: https://www.google.com/maps/search/?api=1&query=BBB%20Rooms%20Centro%20Belem%20PA&query_place_id=ChIJA-NLVpKOpJIRiJz7-bT-9V4 | L55: SEM | M55: SEM | N55: 0
A56: BBB Rooms Marechal Rondon Ji-Paraná RO | B56: 0 | C56: 0 | D56: Av. Mal. Rondon, 1845 - Centro, Ji-Paraná - RO (in Hotel Nova Era) | E56: Ji-Paraná | F56: Rondônia | G56: BR | J56: Hotel | K56: https://www.google.com/maps/search/?api=1&query=BBB%20Rooms%20Marechal%20Rondon%20Ji-Paran%C3%A1%20RO&query_place_id=ChIJhUrFAhWbyZMRWjoGEUaNOtI | L56: SEM | M56: SEM | N56: 0
A57: Bianca | B57: 0 | C57: 0 | E57: Linhares | F57: Espírito Santo | G57: BR | J57: Hotel | K57: https://www.google.com/maps/search/?api=1&query=Bianca&query_place_id=ChIJo50BEAAltgARizdLX_RWdO4 | L57: SEM | M57: SEM | N57: 0
A58: Botucatu são Paulo | B58: 0 | C58: 0 | D58: Castelo Branco | E58: Castelo | F58: Espírito Santo | G58: BR | J58: Hotel | K58: https://www.google.com/maps/search/?api=1&query=Botucatu%20s%C3%A3o%20Paulo&query_place_id=ChIJm7EzFAB9uQARHVgfdd4x6lo | L58: SEM | M58: SEM | N58: 0
A59: Brisa | B59: 0 | C59: 0 | D59: R. Ananias Neto, 177 - Lj | E59: Aracruz | F59: Espírito Santo | G59: BR | J59: Hotel | K59: https://www.google.com/maps/search/?api=1&query=Brisa&query_place_id=ChIJs6CHr4PqtwARiUmypIGLYgU | L59: SEM | M59: SEM | N59: 0
A60: Bristol Hotel Marambaia (em obras) | B60: 0 | C60: 0 | D60: Av. Pedro Álvares Cabral, 9031 | E60: Belém | F60: Pará | G60: BR | H60: https://bristolhoteis.com.br/ | J60: Hotel | K60: https://www.google.com/maps/search/?api=1&query=Bristol%20Hotel%20Marambaia%20(em%20obras)&query_place_id=ChIJYeaQcQCLpJIRdXB7PopEcw0 | L60: COM | M60: COM | N60: 0
A61: Brunei - Retiro Espiritual | B61: 0 | C61: 0 | D61: Estr. Francisca de Oliveira Vieira, 246 | E61: Porto Alegre | F61: Rio Grande do Sul | G61: BR | J61: Hotel | K61: https://www.google.com/maps/search/?api=1&query=Brunei%20-%20Retiro%20Espiritual&query_place_id=ChIJg471RnyFGZUR6aadFtJtpDk | L61: SEM | M61: SEM | N61: 0
A62: BuenosAires | B62: 0 | C62: 0 | D62: Conjunto Residencial, S/N | E62: Sirinhaém | F62: Pernambuco | G62: BR | J62: Hotel | K62: https://www.google.com/maps/search/?api=1&query=BuenosAires&query_place_id=ChIJI17kOQCFqgcRtc1HfFOsdJA | L62: SEM | M62: SEM | N62: 0
A63: ByB | B63: 0 | C63: 0 | D63: 31 Rua Miguel Lemos Miguel Lemos y nossa de | E63: Rio de Janeiro | F63: Rio de Janeiro | G63: BR | I63: +55 21 98014-3363 | J63: Albergue | K63: https://www.google.com/maps/search/?api=1&query=ByB&query_place_id=ChIJd8momEDVmwARyA2FlaBIh3Y | L63: SEM | M63: SEM | N63: 0
A64: C&C_Casa amarela | B64: 0 | C64: 0 | E64: Santana do Araguaia | F64: Pará | G64: BR | J64: Albergue | K64: https://www.google.com/maps/search/?api=1&query=C%26C_Casa%20amarela&query_place_id=ChIJkTj22IZLH5MRvacqe3lO7mg | L64: SEM | M64: SEM | N64: 0
A65: Cachorro | B65: 0 | C65: 0 | D65: R. Alexander Graham Bell, 679 | E65: Londrina | F65: Paraná | G65: BR | J65: Albergue | K65: https://www.google.com/maps/search/?api=1&query=Cachorro&query_place_id=ChIJ5dldCgBb65QRD8JqdToryzo | L65: SEM | M65: SEM | N65: 0
A66: California Hotel | B66: 0 | C66: 0 | E66: São Mateus | F66: Espírito Santo | G66: BR | J66: Hotel | K66: https://www.google.com/maps/search/?api=1&query=California%20Hotel&query_place_id=ChIJ64n6ZFwMygARDMZL3MUDDBY | L66: SEM | M66: SEM | N66: 0
A67: Camping PRT Jazcuri | B67: 0 | C67: 0 | D67: Rio Trombetas zona rural | E67: Oriximiná | F67: Pará | G67: BR | I67: +55 91 98559-8851 | J67: Hotel | K67: https://www.google.com/maps/search/?api=1&query=Camping%20PRT%20Jazcuri&query_place_id=ChIJzVhhOhFNeZIR9R0-iLG3orI | L67: SEM | M67: SEM | N67: 0
A68: Candeias Everest | B68: 0 | C68: 0 | D68: Av. da Cavalhada | E68: Porto Alegre | F68: Rio Grande do Sul | G68: BR | I68: +55 51 3136-4017 | J68: Hotel | K68: https://www.google.com/maps/search/?api=1&query=Candeias%20Everest&query_place_id=ChIJATwKeuGDGZURSGlaGNPfyLQ | L68: SEM | M68: SEM | N68: 0
A69: canela | B69: 0 | C69: 0 | D69: Av. Cel. Marcos, 627 | E69: Porto Alegre | F69: Rio Grande do Sul | G69: BR | J69: Hotel | K69: https://www.google.com/maps/search/?api=1&query=canela&query_place_id=ChIJFWA3CNSDGZURIaClFk_5t3k | L69: SEM | M69: SEM | N69: 0
A70: Caosripa cb | B70: 0 | C70: 0 | D70: Crubixá, Alfredo Chaves | E70: João Neiva | F70: Espírito Santo | G70: BR | J70: Hotel | K70: https://www.google.com/maps/search/?api=1&query=Caosripa%20cb&query_place_id=ChIJ_Z6rJgC_twARhlJUGYvEH0o | L70: SEM | M70: SEM | N70: 0
A71: Capri Motel | B71: 0 | C71: 0 | D71: Av. Castelo Branco, 700 | E71: Crato | F71: Ceará | G71: BR | H71: http://instagram.com/caprimotelcrato | I71: +55 88 2157-9418 | J71: Motel | K71: https://www.google.com/maps/search/?api=1&query=Capri%20Motel&query_place_id=ChIJMzyWYa-DoQcR4iLnzXk9oRU | L71: COM | M71: COM | N71: 0
A72: Carlos trem filho | B72: 0 | C72: 0 | D72: Av. Juscelino Kubitschek de Oliveira, 330 | E72: Porto Alegre | F72: Rio Grande do Sul | G72: BR | J72: Hotel | K72: https://www.google.com/maps/search/?api=1&query=Carlos%20trem%20filho&query_place_id=ChIJFRUpKAB3GZUR1o2H2Peq3HE | L72: SEM | M72: SEM | N72: 0
A73: cas ozimar | B73: 0 | C73: 0 | D73: R. Ribeirão Claro, 193 | E73: Curitiba | F73: Paraná | G73: BR | J73: Albergue | K73: https://www.google.com/maps/search/?api=1&query=cas%20ozimar&query_place_id=ChIJo1ftKkXj3JQRzP9lDo8EEdc | L73: SEM | M73: SEM | N73: 0
A74: Casa Amazônica | B74: 0 | C74: 0 | D74: Rua Dona Sulamita, 100 | E74: Manaus | F74: Amazonas | G74: BR | I74: +55 92 99351-3171 | J74: Albergue | K74: https://www.google.com/maps/search/?api=1&query=Casa%20Amaz%C3%B4nica&query_place_id=ChIJAQDA-7EabJIR5vAf6j4VLoM | L74: SEM | M74: SEM | N74: 0
A75: Casa Amélia | B75: 0 | C75: 0 | D75: BR-135, 05 | E75: São Luís | F75: Maranhão | G75: BR | J75: Apartamento | K75: https://www.google.com/maps/search/?api=1&query=Casa%20Am%C3%A9lia&query_place_id=ChIJ8xXuYK-E9gcR6RUIFIM2oWY | L75: SEM | M75: SEM | N75: 0
A76: Casa Bambuê | B76: 0 | C76: 0 | D76: Tv. Angustura, 3866 | E76: Belém | F76: Pará | G76: BR | I76: +55 91 98170-5733 | J76: Hospedagem | K76: https://www.google.com/maps/search/?api=1&query=Casa%20Bambu%C3%AA&query_place_id=ChIJdTSI_KmNpJIRRLOzHmrE5tI | L76: SEM | M76: SEM | N76: 0
A77: Casa da Árvore | B77: 0 | C77: 0 | D77: Rua Professor Luiz Antônio Lopes, 16 | E77: Porto Alegre | F77: Rio Grande do Sul | G77: BR | J77: Albergue | K77: https://www.google.com/maps/search/?api=1&query=Casa%20da%20%C3%81rvore&query_place_id=ChIJoa2YXSR3GZURIq1ACo8KgcQ | L77: SEM | M77: SEM | N77: 0
A78: Casa da Duluty | B78: 0 | C78: 0 | D78: Av. dos Morangos, 369 | E78: Macapá | F78: Amapá | G78: BR | J78: Hotel | K78: https://www.google.com/maps/search/?api=1&query=Casa%20da%20Duluty&query_place_id=ChIJrUqyjmnnYY0R7-6hybuGIzA | L78: SEM | M78: SEM | N78: 0
A79: Casa da jenny | B79: 0 | C79: 0 | D79: Tv. da Estrella, 60 | E79: Belém | F79: Pará | G79: BR | I79: +55 91 98521-7750 | J79: Casa de temporada | K79: https://www.google.com/maps/search/?api=1&query=Casa%20da%20jenny&query_place_id=ChIJgfkHuSqNpJIRi4l7d9_YtwY | L79: SEM | M79: SEM | N79: 0
A80: Casa da Selma | B80: 0 | C80: 0 | D80: R. Petrolina, 903 | E80: Macapá | F80: Amapá | G80: BR | J80: Alojamento | K80: https://www.google.com/maps/search/?api=1&query=Casa%20da%20Selma&query_place_id=ChIJRbJWVVTnYY0RPMeXgUIYjvM | L80: SEM | M80: SEM | N80: 0
A81: Casa da Serra Pousada | B81: 0 | C81: 0 | D81: R. Ipiranga, km 13 | E81: Morretes | F81: Paraná | G81: BR | I81: +55 41 98758-3838 | J81: Albergue | K81: https://www.google.com/maps/search/?api=1&query=Casa%20da%20Serra%20Pousada&query_place_id=ChIJk5qEPACF3JQRuMkSAjIweys | L81: SEM | M81: SEM | N81: 0
A82: Casa da vó | B82: 0 | C82: 0 | D82: 1687, R. Visc. do Rio Branco, Rua | E82: Curitiba | F82: Paraná | G82: BR | I82: +55 41 99891-4090 | J82: Albergue | K82: https://www.google.com/maps/search/?api=1&query=Casa%20da%20v%C3%B3&query_place_id=ChIJ__9DpXPk3JQRBxaJwAxfc34 | L82: SEM | M82: SEM | N82: 0
A83: Casa da vó Nazaré | B83: 0 | C83: 0 | D83: Passagem São Pedro, 37 | E83: Belém | F83: Pará | G83: BR | J83: Casa de temporada | K83: https://www.google.com/maps/search/?api=1&query=Casa%20da%20v%C3%B3%20Nazar%C3%A9&query_place_id=ChIJLRnhNACNpJIRoIZayRW320s | L83: SEM | M83: SEM | N83: 0
A84: Casa das Almeida | B84: 0 | C84: 0 | D84: R. Santo expedito | E84: Macapá | F84: Amapá | G84: BR | I84: +55 96 98435-9643 | J84: Casa de temporada | K84: https://www.google.com/maps/search/?api=1&query=Casa%20das%20Almeida&query_place_id=ChIJD3S_rPLnYY0RiinMhpYjDMU | L84: SEM | M84: SEM | N84: 0
A85: Casa das Matrizes | B85: 0 | C85: 0 | D85: R. Antônio Rayol | E85: São Luís | F85: Maranhão | G85: BR | J85: Pensão | K85: https://www.google.com/maps/search/?api=1&query=Casa%20das%20Matrizes&query_place_id=ChIJxeVFv3aP9gcR64R2HDnc42U | L85: SEM | M85: SEM | N85: 0
A86: CASA DE ACOLHIMENTO ASSISTÊNCIA MUNICIPAL | B86: 0 | C86: 0 | D86: Av. Miguel Labanca | E86: São Lourenço da Mata | F86: Pernambuco | G86: BR | J86: Albergue | K86: https://www.google.com/maps/search/?api=1&query=CASA%20DE%20ACOLHIMENTO%20ASSIST%C3%8ANCIA%20MUNICIPAL&query_place_id=ChIJEz7mKJkFqwcRR1t8VHKbQFA | L86: SEM | M86: SEM | N86: 0
A87: Casa de Alexandre Araujo | B87: 0 | C87: 0 | D87: R. Cel. Eurípedes Bezerra, 1500 | E87: São Luís | F87: Maranhão | G87: BR | J87: Cama e café | K87: https://www.google.com/maps/search/?api=1&query=Casa%20de%20Alexandre%20Araujo&query_place_id=ChIJ18DaBgCR9gcRkZ3VKPEjQU4 | L87: SEM | M87: SEM | N87: 0
A88: Casa de Apoio Antonieta de Barros | B88: 0 | C88: 0 | D88: Al. das Acácias, 109 | E88: Belém | F88: Pará | G88: BR | H88: https://sinasefepa.org.br/site/casa-antonieta-de-barros/ | I88: +55 91 2121-0927 | J88: Hospedagem | K88: https://www.google.com/maps/search/?api=1&query=Casa%20de%20Apoio%20Antonieta%20de%20Barros&query_place_id=ChIJcfMdZhKNpJIR66J7gcGy6SE | L88: COM | M88: COM | N88: 0
A89: Casa de Apoio Bacabal | B89: 0 | C89: 0 | D89: R. do Norte, 228 | E89: São Luís | F89: Maranhão | G89: BR | J89: Hospedagem | K89: https://www.google.com/maps/search/?api=1&query=Casa%20de%20Apoio%20Bacabal&query_place_id=ChIJM_lWQgCP9gcREeGsBBGnIcY | L89: SEM | M89: SEM | N89: 0
A90: Casa de Apoio de Afrânio | B90: 0 | C90: 0 | D90: Av. Pernambuco, 197 | E90: Petrolina | F90: Pernambuco | G90: BR | J90: Albergue | K90: https://www.google.com/maps/search/?api=1&query=Casa%20de%20Apoio%20de%20Afr%C3%A2nio&query_place_id=ChIJ87UwCABxcwcR1xdHQMqpys4 | L90: SEM | M90: SEM | N90: 0
A91: Casa de Apoio de Altamira | B91: 0 | C91: 0 | D91: Tv. Humaitá, 2676 | E91: Belém | F91: Pará | G91: BR | J91: Hospedagem | K91: https://www.google.com/maps/search/?api=1&query=Casa%20de%20Apoio%20de%20Altamira&query_place_id=ChIJPd4UPQCNpJIR-Dxaf4aPiyM | L91: SEM | M91: SEM | N91: 0
A92: Casa de Apoio de Juruti - Unidade Itaituba | B92: 0 | C92: 0 | D92: Alameda Beira Rio | E92: Itaituba | F92: Pará | G92: BR | J92: Albergue | K92: https://www.google.com/maps/search/?api=1&query=Casa%20de%20Apoio%20de%20Juruti%20-%20Unidade%20Itaituba&query_place_id=ChIJzQepMwDbX5IRM3feMCfjLDo | L92: SEM | M92: SEM | N92: 0
A93: Casa de Apoio Flora D'Avila | B93: 0 | C93: 0 | D93: R. Padre Adolfo Rhol, 455 | E93: Ji-Paraná | F93: Rondônia | G93: BR | I93: +55 69 99373-0284 | J93: Albergue | K93: https://www.google.com/maps/search/?api=1&query=Casa%20de%20Apoio%20Flora%20D'Avila&query_place_id=ChIJLXGwVACbyZMRdbHQt1NWfPc | L93: SEM | M93: SEM | N93: 0
A94: casa de apoio princesa Curitiba | B94: 0 | C94: 0 | D94: R. Comendador Roseira, 122 | E94: Curitiba | F94: Paraná | G94: BR | J94: Albergue | K94: https://www.google.com/maps/search/?api=1&query=casa%20de%20apoio%20princesa%20Curitiba&query_place_id=ChIJnVJkEwDl3JQRxQFJFp0_rPw | L94: SEM | M94: SEM | N94: 0
A95: Casa de Apoio São Luís Gonzaga | B95: 0 | C95: 0 | D95: R. do Norte, 327 | E95: São Luís | F95: Maranhão | G95: BR | J95: Hospedagem | K95: https://www.google.com/maps/search/?api=1&query=Casa%20de%20Apoio%20S%C3%A3o%20Lu%C3%ADs%20Gonzaga&query_place_id=ChIJDepV1KSP9gcRuXSO3rVOIAw | L95: SEM | M95: SEM | N95: 0
A96: Casa de Elane | B96: 0 | C96: 0 | D96: R. Pereira Muniz, 09 | E96: São Luís | F96: Maranhão | G96: BR | I96: +55 98 98870-6859 | J96: Hotel | K96: https://www.google.com/maps/search/?api=1&query=Casa%20de%20Elane&query_place_id=ChIJdSZISeOT9gcRQsuWEYV8YFg | L96: SEM | M96: SEM | N96: 0
A97: Casa De Maria | B97: 0 | C97: 0 | D97: R. Nove, 11 | E97: São Luís | F97: Maranhão | G97: BR | J97: Alojamento | K97: https://www.google.com/maps/search/?api=1&query=Casa%20De%20Maria&query_place_id=ChIJ3y1eRySS9gcR-9LnEYIA7Pc | L97: SEM | M97: SEM | N97: 0
A98: Casa De Maria | B98: 0 | C98: 0 | D98: Av. Rômulo Maiorana, 1654 | E98: Belém | F98: Pará | G98: BR | J98: Alojamento | K98: https://www.google.com/maps/search/?api=1&query=Casa%20De%20Maria&query_place_id=ChIJqVjeYQuMpJIRaDB-Ma1r-0E | L98: SEM | M98: SEM | N98: 0
A99: Casa de Passagem Belém | B99: 0 | C99: 0 | D99: R. Rubéns Cardoso de Brito, 226 | E99: Curitiba | F99: Paraná | G99: BR | J99: Albergue | K99: https://www.google.com/maps/search/?api=1&query=Casa%20de%20Passagem%20Bel%C3%A9m&query_place_id=ChIJs0evlgzl3JQRCKF88KDOUew | L99: SEM | M99: SEM | N99: 0
A100: Casa de passagem de Irati | B100: 0 | C100: 0 | D100: Av. Pres. Getúlio Vargas, 3008 | E100: Irati | F100: Paraná | G100: BR | I100: +55 42 99909-9899 | J100: Albergue | K100: https://www.google.com/maps/search/?api=1&query=Casa%20de%20passagem%20de%20Irati&query_place_id=ChIJWeuIdADV55QRnHLOEt9nIAk | L100: SEM | M100: SEM | N100: 0
...

Sheet Estatísticas
A1: Estatísticas Descritivas | B1: Reviews sem site | C1: Reviews com site | D1: TotalScore sem site | E1: TotalScore com site
A2: Média | B2: {=AVERAGE(_xlfn._xlws.FILTER(Dados!C:C,NOT(ISTEXT(Dados!H:H))))} -> 89.853137 | C2: {=AVERAGE(_xlfn._xlws.FILTER(Dados!C:C,ISTEXT(Dados!H:H)))} -> 778.71957 | D2: {=AVERAGE(_xlfn._xlws.FILTER(Dados!B:B,NOT(ISTEXT(Dados!H:H))))} -> 3.7049077 | E2: {=AVERAGE(_xlfn._xlws.FILTER(Dados!B:B,ISTEXT(Dados!H:H)))} -> 4.3372958
A3: Mediana | B3: {=MEDIAN(_xlfn._xlws.FILTER(Dados!C:C,NOT(ISTEXT(Dados!H:H))))} -> 25 | C3: {=MEDIAN(_xlfn._xlws.FILTER(Dados!C:C,ISTEXT(Dados!H:H)))} -> 297 | D3: {=MEDIAN(_xlfn._xlws.FILTER(Dados!B:B,NOT(ISTEXT(Dados!H:H))))} -> 4.2 | E3: {=MEDIAN(_xlfn._xlws.FILTER(Dados!B:B,ISTEXT(Dados!H:H)))} -> 4.4
A4: Moda | B4: {=_xlfn.MODE.SNGL(_xlfn._xlws.FILTER(Dados!C:C,NOT(ISTEXT(Dados!H:H))))} -> 0 | C4: {=_xlfn.MODE.SNGL(_xlfn._xlws.FILTER(Dados!C:C,ISTEXT(Dados!H:H)))} -> 0 | D4: {=_xlfn.MODE.SNGL(_xlfn._xlws.FILTER(Dados!B:B,NOT(ISTEXT(Dados!H:H))))} -> 0 | E4: {=_xlfn.MODE.SNGL(_xlfn._xlws.FILTER(Dados!B:B,ISTEXT(Dados!H:H)))} -> 4.5
A5: Desvio Padrão | B5: {=_xlfn.STDEV.S(_xlfn._xlws.FILTER(Dados!C:C,NOT(ISTEXT(Dados!H:H))))} -> 184.48875 | C5: {=_xlfn.STDEV.S(_xlfn._xlws.FILTER(Dados!C:C,ISTEXT(Dados!H:H)))} -> 1573.5366 | D5: {=_xlfn.STDEV.S(_xlfn._xlws.FILTER(Dados!B:B,NOT(ISTEXT(Dados!H:H))))} -> 1.541785 | E5: {=_xlfn.STDEV.S(_xlfn._xlws.FILTER(Dados!B:B,ISTEXT(Dados!H:H)))} -> 0.59146289
A6: Variância | B6: {=_xlfn.VAR.S(_xlfn._xlws.FILTER(Dados!C:C,NOT(ISTEXT(Dados!H:H))))} -> 34036.098 | C6: {=_xlfn.VAR.S(_xlfn._xlws.FILTER(Dados!C:C,ISTEXT(Dados!H:H)))} -> 2476017.6 | D6: {=_xlfn.VAR.S(_xlfn._xlws.FILTER(Dados!B:B,NOT(ISTEXT(Dados!H:H))))} -> 2.3771008 | E6: {=_xlfn.VAR.S(_xlfn._xlws.FILTER(Dados!B:B,ISTEXT(Dados!H:H)))} -> 0.34982835
A7: Mínimo | B7: {=MIN(_xlfn._xlws.FILTER(Dados!C:C,NOT(ISTEXT(Dados!H:H))))} -> 0 | C7: {=MIN(_xlfn._xlws.FILTER(Dados!C:C,ISTEXT(Dados!H:H)))} -> 0 | D7: {=MIN(_xlfn._xlws.FILTER(Dados!B:B,NOT(ISTEXT(Dados!H:H))))} -> 0 | E7: {=MIN(_xlfn._xlws.FILTER(Dados!B:B,ISTEXT(Dados!H:H)))} -> 0
A8: Máximo | B8: {=MAX(_xlfn._xlws.FILTER(Dados!C:C,NOT(ISTEXT(Dados!H:H))))} -> 3686 | C8: {=MAX(_xlfn._xlws.FILTER(Dados!C:C,ISTEXT(Dados!H:H)))} -> 41749 | D8: {=MAX(_xlfn._xlws.FILTER(Dados!B:B,NOT(ISTEXT(Dados!H:H))))} -> 5 | E8: {=MAX(_xlfn._xlws.FILTER(Dados!B:B,ISTEXT(Dados!H:H)))} -> 5
A9: Contagem | B9: {=COUNT(_xlfn._xlws.FILTER(Dados!C:C,NOT(ISTEXT(Dados!H:H))))} -> 5420 | C9: {=COUNT(_xlfn._xlws.FILTER(Dados!C:C,ISTEXT(Dados!H:H)))} -> 4896 | D9: {=COUNT(_xlfn._xlws.FILTER(Dados!B:B,NOT(ISTEXT(Dados!H:H))))} -> 5420 | E9: {=COUNT(_xlfn._xlws.FILTER(Dados!B:B,ISTEXT(Dados!H:H)))} -> 4896
A11: Quartis | B11: Reviews sem site | C11: Reviews com site | D11: TotalScore sem site | E11: TotalScore com site
A12: Q1 25% | B12: {=_xlfn.PERCENTILE.INC(_xlfn._xlws.FILTER(Dados!C:C,NOT(ISTEXT(Dados!H:H))),0.25)} -> 3 | C12: {=_xlfn.PERCENTILE.INC(_xlfn._xlws.FILTER(Dados!C:C,ISTEXT(Dados!H:H)),0.25)} -> 98 | D12: {=_xlfn.PERCENTILE.INC(_xlfn._xlws.FILTER(Dados!B:B,NOT(ISTEXT(Dados!H:H))),0.25)} -> 3.7 | E12: {=_xlfn.PERCENTILE.INC(_xlfn._xlws.FILTER(Dados!B:B,ISTEXT(Dados!H:H)),0.25)} -> 4.2
A13: Q2 50% | B13: {=_xlfn.PERCENTILE.INC(_xlfn._xlws.FILTER(Dados!C:C,NOT(ISTEXT(Dados!H:H))),0.5)} -> 25 | C13: {=_xlfn.PERCENTILE.INC(_xlfn._xlws.FILTER(Dados!C:C,ISTEXT(Dados!H:H)),0.5)} -> 297 | D13: {=_xlfn.PERCENTILE.INC(_xlfn._xlws.FILTER(Dados!B:B,NOT(ISTEXT(Dados!H:H))),0.5)} -> 4.2 | E13: {=_xlfn.PERCENTILE.INC(_xlfn._xlws.FILTER(Dados!B:B,ISTEXT(Dados!H:H)),0.5)} -> 4.4
A14: Q3 75% | B14: {=_xlfn.PERCENTILE.INC(_xlfn._xlws.FILTER(Dados!C:C,NOT(ISTEXT(Dados!H:H))),0.75)} -> 104 | C14: {=_xlfn.PERCENTILE.INC(_xlfn._xlws.FILTER(Dados!C:C,ISTEXT(Dados!H:H)),0.75)} -> 790 | D14: {=_xlfn.PERCENTILE.INC(_xlfn._xlws.FILTER(Dados!B:B,NOT(ISTEXT(Dados!H:H))),0.75)} -> 4.6 | E14: {=_xlfn.PERCENTILE.INC(_xlfn._xlws.FILTER(Dados!B:B,ISTEXT(Dados!H:H)),0.75)} -> 4.7
A16: Curtose e Assimetria | B16: Reviews sem site | C16: Reviews com site | D16: TotalScore sem Site | E16: TotalScore com site
A17: Curtose | B17: {=KURT(_xlfn._xlws.FILTER(Dados!C:C,NOT(ISTEXT(Dados!H:H))))} -> 76.581728 | C17: {=KURT(_xlfn._xlws.FILTER(Dados!C:C,ISTEXT(Dados!H:H)))} -> 159.52779 | D17: {=KURT(_xlfn._xlws.FILTER(Dados!B:B,NOT(ISTEXT(Dados!H:H))))} -> 1.5133051 | E17: {=KURT(_xlfn._xlws.FILTER(Dados!B:B,ISTEXT(Dados!H:H)))} -> 27.080595
A18: Assimetria | B18: {=SKEW(_xlfn._xlws.FILTER(Dados!C:C,NOT(ISTEXT(Dados!H:H))))} -> 6.525325 | C18: {=SKEW(_xlfn._xlws.FILTER(Dados!C:C,ISTEXT(Dados!H:H)))} -> 9.0225747 | D18: {=SKEW(_xlfn._xlws.FILTER(Dados!B:B,NOT(ISTEXT(Dados!H:H))))} -> -1.6979081 | E18: {=SKEW(_xlfn._xlws.FILTER(Dados!B:B,ISTEXT(Dados!H:H)))} -> -4.1999918
A20: Covariância | B20: Reviews/TotalScore sem site | C20: Reviews/TotalScore com site
A21: Valor | B21: {=_xlfn.COVARIANCE.S(_xlfn._xlws.FILTER(Dados!B:B,NOT(ISTEXT(Dados!H:H))),_xlfn._xlws.FILTER(Dados!C:C,NOT(ISTEXT(Dados!H:H))))} -> 44.335524 | C21: {=_xlfn.COVARIANCE.S(_xlfn._xlws.FILTER(Dados!B:B,ISTEXT(Dados!H:H)),_xlfn._xlws.FILTER(Dados!C:C,ISTEXT(Dados!H:H)))} -> 20.204782
A23: Amplitude | B23: Reviews sem site | C23: Reviews com site | D23: TotalScore sem site | E23: TotalScore com site
A24: Valor | B24: =B8-B7 -> 3686 | C24: =C8-C7 -> 41749 | D24: =D8-D7 -> 5 | E24: =E8-E7 -> 5
A26: Coeficiente de Variação | B26: Reviews sem site | C26: Reviews com site | D26: TotalScore sem site | E26: TotalScore com site
A27: Valor | B27: =(B5/B2) -> 2.0532255 | C27: =(C5/C2) -> 2.0206718 | D27: =(D5/D2) -> 0.41614665 | E27: =(E5/E2) -> 0.13636674

Sheet Gráficos
